{
  "annotations": {
    "list": [
      {
        "builtIn": 1,
        "datasource": "-- Grafana --",
        "enable": true,
        "hide": true,
        "iconColor": "rgba(0, 211, 255, 1)",
        "name": "Annotations & Alerts",
        "target": {
          "limit": 100,
          "matchAny": false,
          "tags": [],
          "type": "dashboard"
        },
        "type": "dashboard"
      }
    ]
  },
  "editable": true,
  "fiscalYearStartMonth": 0,
  "gnetId": null,
  "graphTooltip": 0,
  "id": 59,
  "iteration": 1644409276099,
  "links": [],
  "liveNow": false,
  "panels": [
    {
      "datasource": null,
      "fieldConfig": {
        "defaults": {
          "color": {
            "mode": "thresholds"
          },
          "custom": {
            "align": "auto",
            "displayMode": "auto"
          },
          "mappings": [],
          "thresholds": {
            "mode": "absolute",
            "steps": [
              {
                "color": "green",
                "value": null
              },
              {
                "color": "red",
                "value": 80
              }
            ]
          }
        },
        "overrides": [
          {
            "matcher": {
              "id": "byName",
              "options": "__name__"
            },
            "properties": [
              {
                "id": "custom.width",
                "value": 1814
              }
            ]
          },
          {
            "matcher": {
              "id": "byName",
              "options": "container"
            },
            "properties": [
              {
                "id": "custom.width",
                "value": 218
              }
            ]
          }
        ]
      },
      "gridPos": {
        "h": 20,
        "w": 24,
        "x": 0,
        "y": 0
      },
      "id": 2,
      "options": {
        "showHeader": true,
        "sortBy": []
      },
      "pluginVersion": "8.2.2",
      "targets": [
        {
          "exemplar": true,
          "expr": "({__name__!=\"\", container='$deployment', namespace='$namespace'})",
          "format": "table",
          "interval": "",
          "legendFormat": "",
          "refId": "A"
        }
      ],
      "title": "All metrics for $deployment",
      "transformations": [
        {
          "id": "sortBy",
          "options": {
            "fields": {},
            "sort": [
              {
                "desc": true,
                "field": "Time"
              }
            ]
          }
        },
        {
          "id": "groupBy",
          "options": {
            "fields": {
              "__name__": {
                "aggregations": [],
                "operation": "groupby"
              }
            }
          }
        },
        {
          "id": "organize",
          "options": {
            "excludeByName": {
              "action": true,
              "code": true,
              "component": true,
              "consumer": true,
              "consumerType": true,
              "container_id": true,
              "controller": true,
              "cpu": true,
              "device": true,
              "endpoint": true,
              "failure_type": true,
              "generation": true,
              "id": true,
              "image": true,
              "image_id": true,
              "image_spec": true,
              "instance": true,
              "job": true,
              "le": false,
              "messageType": true,
              "method": true,
              "name": false,
              "namespace": true,
              "node": true,
              "pod": true,
              "prometheus": true,
              "reason": true,
              "resource": true,
              "scope": true,
              "service": true,
              "state": true,
              "topic": true,
              "uid": true,
              "ulimit": true,
              "unit": true
            },
            "indexByName": {},
            "renameByName": {
              "__name__": "Metric name"
            }
          }
        }
      ],
      "type": "table"
    }
  ],
  "schemaVersion": 31,
  "style": "dark",
  "tags": [],
  "templating": {
    "list": [
      {
        "allValue": null,
        "current": {
          "selected": true,
          "text": "test1",
          "value": "test1"
        },
        "datasource": null,
        "definition": "label_values(namespace)",
        "description": null,
        "error": null,
        "hide": 0,
        "includeAll": false,
        "label": "Namespace",
        "multi": false,
        "name": "namespace",
        "options": [],
        "query": {
          "query": "label_values(namespace)",
          "refId": "StandardVariableQuery"
        },
        "refresh": 1,
        "regex": "",
        "skipUrlSync": false,
        "sort": 1,
        "type": "query"
      },
      {
        "allValue": null,
        "current": {
          "selected": true,
          "text": "sa-component-testportal",
          "value": "sa-component-testportal"
        },
        "datasource": null,
        "definition": "label_values(kube_deployment_labels{namespace=\"$namespace\"},deployment)",
        "description": null,
        "error": null,
        "hide": 0,
        "includeAll": false,
        "label": "Deployment",
        "multi": false,
        "name": "deployment",
        "options": [],
        "query": {
          "query": "label_values(kube_deployment_labels{namespace=\"$namespace\"},deployment)",
          "refId": "StandardVariableQuery"
        },
        "refresh": 1,
        "regex": "",
        "skipUrlSync": false,
        "sort": 1,
        "type": "query"
      }
    ]
  },
  "time": {
    "from": "now-30s",
    "to": "now"
  },
  "timepicker": {},
  "timezone": "",
  "title": "Deployment metrics inspector",
  "uid": "Sq09jJ-7z",
  "version": 3
}